{
    "train_avg_precision": {
        "best_results": [
            1.0,
            1.0,
            1.0,
            1.0,
            1.0
        ],
        "all_results": [
            [
                1.0,
                1.0,
                1.0,
                1.0,
                1.0
            ],
            [
                1.0,
                0.0,
                0.0,
                0.0,
                0.0
            ],
            [
                1.0,
                0.0,
                0.0,
                0.0,
                0.0
            ],
            [
                1.0,
                1.0,
                0.0,
                0.0,
                0.0
            ],
            [
                1.0,
                1.0,
                0.0,
                1.0,
                0.0
            ],
            [
                1.0,
                1.0,
                0.0,
                1.0,
                0.0
            ]
        ],
        "epoches": [
            0,
            10,
            20,
            30,
            40,
            50
        ]
    },
    "train_avg_recall": {
        "best_results": [
            0.97,
            0.44,
            0.38333333333333336,
            0.4166666666666667,
            0.16
        ],
        "all_results": [
            [
                0.97,
                0.44,
                0.38333333333333336,
                0.4166666666666667,
                0.16
            ],
            [
                0.97,
                0.0,
                0.0,
                0.0,
                0.0
            ],
            [
                0.97,
                0.0,
                0.0,
                0.0,
                0.0
            ],
            [
                0.97,
                0.44,
                0.0,
                0.0,
                0.0
            ],
            [
                0.97,
                0.44,
                0.0,
                0.4166666666666667,
                0.0
            ],
            [
                0.97,
                0.44,
                0.0,
                0.4166666666666667,
                0.0
            ]
        ],
        "epoches": [
            0,
            10,
            20,
            30,
            40,
            50
        ]
    },
    "train_avg_f1": {
        "best_results": [
            0.9847715736040609,
            0.6111111111111112,
            0.5542168674698795,
            0.5882352941176471,
            0.2758620689655173
        ],
        "all_results": [
            [
                0.9847715736040609,
                0.6111111111111112,
                0.5542168674698795,
                0.5882352941176471,
                0.2758620689655173
            ],
            [
                0.9847715736040609,
                0.0,
                0.0,
                0.0,
                0.0
            ],
            [
                0.9847715736040609,
                0.0,
                0.0,
                0.0,
                0.0
            ],
            [
                0.9847715736040609,
                0.6111111111111112,
                0.0,
                0.0,
                0.0
            ],
            [
                0.9847715736040609,
                0.6111111111111112,
                0.0,
                0.5882352941176471,
                0.0
            ],
            [
                0.9847715736040609,
                0.6111111111111112,
                0.0,
                0.5882352941176471,
                0.0
            ]
        ],
        "epoches": [
            0,
            10,
            20,
            30,
            40,
            50
        ]
    },
    "train_avg_accuracy": {
        "best_results": [
            0.9700000286102295,
            0.5600000023841858,
            0.6166666746139526,
            0.5833333134651184,
            0.8399999737739563
        ],
        "all_results": [
            [
                0.9700000286102295,
                0.5600000023841858,
                0.6166666746139526,
                0.5833333134651184,
                0.8399999737739563
            ],
            [
                0.9700000286102295,
                0.5600000023841858,
                0.6166666746139526,
                0.5833333134651184,
                0.8399999737739563
            ],
            [
                0.9700000286102295,
                0.5600000023841858,
                0.6166666746139526,
                0.5833333134651184,
                0.8399999737739563
            ],
            [
                0.9700000286102295,
                0.4399999976158142,
                0.6166666746139526,
                0.5833333134651184,
                0.8399999737739563
            ],
            [
                0.9700000286102295,
                0.4399999976158142,
                0.6166666746139526,
                0.4166666567325592,
                0.8399999737739563
            ],
            [
                0.9700000286102295,
                0.4399999976158142,
                0.6166666746139526,
                0.4166666567325592,
                0.8399999737739563
            ]
        ],
        "epoches": [
            0,
            10,
            20,
            30,
            40,
            50
        ]
    },
    "val_avg_precision": {
        "best_results": [
            1.0,
            1.0,
            1.0,
            1.0,
            1.0
        ],
        "all_results": [
            [
                1.0,
                1.0,
                1.0,
                1.0,
                1.0
            ],
            [
                1.0,
                0.0,
                0.0,
                0.0,
                0.0
            ],
            [
                1.0,
                0.0,
                0.0,
                0.0,
                0.0
            ],
            [
                1.0,
                1.0,
                0.0,
                0.0,
                0.0
            ],
            [
                1.0,
                1.0,
                0.0,
                1.0,
                0.0
            ],
            [
                1.0,
                1.0,
                0.01818181818181818,
                1.0,
                0.0
            ]
        ],
        "epoches": [
            0,
            10,
            20,
            30,
            40,
            50
        ]
    },
    "val_avg_recall": {
        "best_results": [
            0.8316831683168316,
            0.5544554455445545,
            1.0,
            0.5346534653465347,
            0.3564356435643564
        ],
        "all_results": [
            [
                0.8316831683168316,
                0.5544554455445545,
                1.0,
                0.5346534653465347,
                0.3564356435643564
            ],
            [
                0.8316831683168316,
                0.0,
                0.0,
                0.0,
                0.0
            ],
            [
                0.8316831683168316,
                0.0,
                0.0,
                0.0,
                0.0
            ],
            [
                0.8316831683168316,
                0.5544554455445545,
                0.0,
                0.0,
                0.0
            ],
            [
                0.8316831683168316,
                0.5544554455445545,
                0.0,
                0.5346534653465347,
                0.0
            ],
            [
                0.8316831683168316,
                0.5544554455445545,
                1.0,
                0.5346534653465347,
                0.0
            ]
        ],
        "epoches": [
            0,
            10,
            20,
            30,
            40,
            50
        ]
    },
    "val_avg_f1": {
        "best_results": [
            0.9081081081081082,
            0.713375796178344,
            0.7051282051282052,
            0.6967741935483871,
            0.5255474452554745
        ],
        "all_results": [
            [
                0.9081081081081082,
                0.713375796178344,
                0.7051282051282052,
                0.6967741935483871,
                0.5255474452554745
            ],
            [
                0.9081081081081082,
                0.0,
                0.0,
                0.0,
                0.0
            ],
            [
                0.9081081081081082,
                0.0,
                0.0,
                0.0,
                0.0
            ],
            [
                0.9081081081081082,
                0.713375796178344,
                0.0,
                0.0,
                0.0
            ],
            [
                0.9081081081081082,
                0.713375796178344,
                0.0,
                0.6967741935483871,
                0.0
            ],
            [
                0.9081081081081082,
                0.713375796178344,
                0.03571428571428572,
                0.6967741935483871,
                0.0
            ]
        ],
        "epoches": [
            0,
            10,
            20,
            30,
            40,
            50
        ]
    },
    "val_avg_accuracy": {
        "best_results": [
            0.8316831588745117,
            0.5544554591178894,
            0.5445544719696045,
            0.5346534848213196,
            0.6435643434524536
        ],
        "all_results": [
            [
                0.8316831588745117,
                0.5544554591178894,
                0.5445544719696045,
                0.5346534848213196,
                0.6435643434524536
            ],
            [
                0.8316831588745117,
                0.4455445408821106,
                0.4554455578327179,
                0.4653465449810028,
                0.6435643434524536
            ],
            [
                0.8316831588745117,
                0.4455445408821106,
                0.4554455578327179,
                0.4653465449810028,
                0.6435643434524536
            ],
            [
                0.8316831588745117,
                0.5544554591178894,
                0.4554455578327179,
                0.4653465449810028,
                0.6435643434524536
            ],
            [
                0.8316831588745117,
                0.5544554591178894,
                0.4554455578327179,
                0.5346534848213196,
                0.6435643434524536
            ],
            [
                0.8316831588745117,
                0.5544554591178894,
                0.4653465449810028,
                0.5346534848213196,
                0.6435643434524536
            ]
        ],
        "epoches": [
            0,
            10,
            20,
            30,
            40,
            50
        ]
    },
    "test_avg_precision": {
        "best_results": [
            1.0,
            1.0,
            1.0,
            1.0,
            1.0
        ],
        "all_results": [
            [
                1.0,
                1.0,
                1.0,
                1.0,
                1.0
            ],
            [
                1.0,
                0.0,
                0.0,
                0.0,
                0.0
            ],
            [
                1.0,
                0.0,
                0.0,
                0.0,
                0.0
            ],
            [
                1.0,
                1.0,
                0.0,
                0.0,
                0.0
            ],
            [
                1.0,
                1.0,
                0.0,
                1.0,
                0.0
            ],
            [
                1.0,
                1.0,
                0.0,
                1.0,
                0.0
            ]
        ],
        "epoches": [
            0,
            10,
            20,
            30,
            40,
            50
        ]
    },
    "test_avg_recall": {
        "best_results": [
            0.7,
            0.62,
            0.57,
            0.55,
            0.4
        ],
        "all_results": [
            [
                0.7,
                0.62,
                0.57,
                0.55,
                0.4
            ],
            [
                0.7,
                0.0,
                0.0,
                0.0,
                0.0
            ],
            [
                0.7,
                0.0,
                0.0,
                0.0,
                0.0
            ],
            [
                0.7,
                0.62,
                0.0,
                0.0,
                0.0
            ],
            [
                0.7,
                0.62,
                0.0,
                0.55,
                0.0
            ],
            [
                0.7,
                0.62,
                0.0,
                0.55,
                0.0
            ]
        ],
        "epoches": [
            0,
            10,
            20,
            30,
            40,
            50
        ]
    },
    "test_avg_f1": {
        "best_results": [
            0.8235294117647058,
            0.7654320987654321,
            0.7261146496815287,
            0.7096774193548387,
            0.5714285714285715
        ],
        "all_results": [
            [
                0.8235294117647058,
                0.7654320987654321,
                0.7261146496815287,
                0.7096774193548387,
                0.5714285714285715
            ],
            [
                0.8235294117647058,
                0.0,
                0.0,
                0.0,
                0.0
            ],
            [
                0.8235294117647058,
                0.0,
                0.0,
                0.0,
                0.0
            ],
            [
                0.8235294117647058,
                0.7654320987654321,
                0.0,
                0.0,
                0.0
            ],
            [
                0.8235294117647058,
                0.7654320987654321,
                0.0,
                0.7096774193548387,
                0.0
            ],
            [
                0.8235294117647058,
                0.7654320987654321,
                0.0,
                0.7096774193548387,
                0.0
            ]
        ],
        "epoches": [
            0,
            10,
            20,
            30,
            40,
            50
        ]
    },
    "test_avg_accuracy": {
        "best_results": [
            0.699999988079071,
            0.6200000047683716,
            0.5699999928474426,
            0.550000011920929,
            0.6000000238418579
        ],
        "all_results": [
            [
                0.699999988079071,
                0.6200000047683716,
                0.5699999928474426,
                0.550000011920929,
                0.6000000238418579
            ],
            [
                0.699999988079071,
                0.3799999952316284,
                0.4300000071525574,
                0.44999998807907104,
                0.6000000238418579
            ],
            [
                0.699999988079071,
                0.3799999952316284,
                0.4300000071525574,
                0.44999998807907104,
                0.6000000238418579
            ],
            [
                0.699999988079071,
                0.6200000047683716,
                0.4300000071525574,
                0.44999998807907104,
                0.6000000238418579
            ],
            [
                0.699999988079071,
                0.6200000047683716,
                0.4300000071525574,
                0.550000011920929,
                0.6000000238418579
            ],
            [
                0.699999988079071,
                0.6200000047683716,
                0.41999998688697815,
                0.550000011920929,
                0.6000000238418579
            ]
        ],
        "epoches": [
            0,
            10,
            20,
            30,
            40,
            50
        ]
    }
}